<?xml version="1.0" encoding="utf-8"?>
<!-- Copyright ©2016 LexisNexis Univentio, The Netherlands. -->
<lexisnexis-patent-document schema-version="1.13" date-produced="20160127" file="EP2939585A1.xml" produced-by="LexisNexis-Univentio" lang="eng" date-inserted="20151104" time-inserted="091318" date-changed="20151110" time-changed="083712">
  <bibliographic-data lang="eng">
    <publication-reference publ-type="Application" publ-desc="Application published with search report">
      <document-id id="121940899">
        <country>EP</country>
        <doc-number>2939585</doc-number>
        <kind>A1</kind>
        <date>20151104</date>
      </document-id>
    </publication-reference>
    <application-reference>
      <document-id>
        <country>EP</country>
        <doc-number>15164721</doc-number>
        <date>20131227</date>
      </document-id>
    </application-reference>
    <language-of-filing>eng</language-of-filing>
    <language-of-publication>eng</language-of-publication>
    <priority-claims date-changed="20151104">
      <priority-claim sequence="1" kind="national">
        <country>IT</country>
        <doc-number>2012PR0092</doc-number>
        <date>20121228</date>
      </priority-claim>
      <priority-claim sequence="2" kind="national">
        <country>IT</country>
        <doc-number>2012PR0093</doc-number>
        <date>20121228</date>
      </priority-claim>
      <priority-claim sequence="1" data-format="docdb">
        <country>IT</country>
        <doc-number>PR20120092</doc-number>
        <kind>A</kind>
        <date>20121228</date>
        <priority-active-indicator>true</priority-active-indicator>
      </priority-claim>
      <priority-claim sequence="2" data-format="docdb">
        <country>IT</country>
        <doc-number>PR20120093</doc-number>
        <kind>A</kind>
        <date>20121228</date>
        <priority-active-indicator>true</priority-active-indicator>
      </priority-claim>
      <priority-claim sequence="3" data-format="docdb">
        <country>EP</country>
        <doc-number>13199631</doc-number>
        <kind>A</kind>
        <date>20131227</date>
        <priority-active-indicator>false</priority-active-indicator>
      </priority-claim>
      <priority-claim sequence="1" data-format="original">
        <doc-number>PR20120092</doc-number>
      </priority-claim>
      <priority-claim sequence="2" data-format="original">
        <doc-number>PR20120093</doc-number>
      </priority-claim>
      <priority-claim sequence="3" data-format="original">
        <doc-number>13199631.6</doc-number>
      </priority-claim>
      <priority-claim sequence="1" data-format="epodoc">
        <doc-number>IT2012PR00092</doc-number>
      </priority-claim>
      <priority-claim sequence="2" data-format="epodoc">
        <doc-number>IT2012PR00093</doc-number>
      </priority-claim>
      <priority-claim sequence="3" data-format="epodoc">
        <doc-number>EP20130199631</doc-number>
      </priority-claim>
    </priority-claims>
    <dates-of-public-availability date-changed="20151105">
      <gazette-reference>
        <date>20151104</date>
      </gazette-reference>
      <unexamined-printed-without-grant>
        <date>20151104</date>
      </unexamined-printed-without-grant>
      <examined-printed-without-grant>
        <date>20151104</date>
      </examined-printed-without-grant>
    </dates-of-public-availability>
    <classifications-ipcr date-changed="20151105">
      <classification-ipcr sequence="1">
        <text>A47L  15/42        20060101AFI20150930BHEP        </text>
        <ipc-version-indicator>
          <date>20060101</date>
        </ipc-version-indicator>
        <classification-level>A</classification-level>
        <section>A</section>
        <class>47</class>
        <subclass>L</subclass>
        <main-group>15</main-group>
        <subgroup>42</subgroup>
        <symbol-position>F</symbol-position>
        <classification-value>I</classification-value>
        <action-date>
          <date>20150930</date>
        </action-date>
        <generating-office>
          <country>EP</country>
        </generating-office>
        <classification-status>B</classification-status>
        <classification-data-source>H</classification-data-source>
      </classification-ipcr>
    </classifications-ipcr>
    <classifications-cpc date-changed="20151105">
      <classification-cpc sequence="1">
        <text>A47L  15/0021      20130101 FI20140428BHEP        </text>
        <cpc-version-indicator>
          <date>20130101</date>
        </cpc-version-indicator>
        <section>A</section>
        <class>47</class>
        <subclass>L</subclass>
        <main-group>15</main-group>
        <subgroup>0021</subgroup>
        <symbol-position>F</symbol-position>
        <classification-value>I</classification-value>
        <action-date>
          <date>20140428</date>
        </action-date>
        <generating-office>
          <country>EP</country>
        </generating-office>
        <classification-status>B</classification-status>
        <classification-data-source>H</classification-data-source>
      </classification-cpc>
      <classification-cpc sequence="2">
        <text>A47L  15/23        20130101 LI20150504BHEP        </text>
        <cpc-version-indicator>
          <date>20130101</date>
        </cpc-version-indicator>
        <section>A</section>
        <class>47</class>
        <subclass>L</subclass>
        <main-group>15</main-group>
        <subgroup>23</subgroup>
        <symbol-position>L</symbol-position>
        <classification-value>I</classification-value>
        <action-date>
          <date>20150504</date>
        </action-date>
        <generating-office>
          <country>EP</country>
        </generating-office>
        <classification-status>B</classification-status>
        <classification-data-source>H</classification-data-source>
      </classification-cpc>
      <classification-cpc sequence="3">
        <text>A47L  15/4282      20130101 LI20150504BHEP        </text>
        <cpc-version-indicator>
          <date>20130101</date>
        </cpc-version-indicator>
        <section>A</section>
        <class>47</class>
        <subclass>L</subclass>
        <main-group>15</main-group>
        <subgroup>4282</subgroup>
        <symbol-position>L</symbol-position>
        <classification-value>I</classification-value>
        <action-date>
          <date>20150504</date>
        </action-date>
        <generating-office>
          <country>EP</country>
        </generating-office>
        <classification-status>B</classification-status>
        <classification-data-source>H</classification-data-source>
      </classification-cpc>
      <classification-cpc sequence="4">
        <text>A47L2401/12        20130101 LA20150504BHEP        </text>
        <cpc-version-indicator>
          <date>20130101</date>
        </cpc-version-indicator>
        <section>A</section>
        <class>47</class>
        <subclass>L</subclass>
        <main-group>2401</main-group>
        <subgroup>12</subgroup>
        <symbol-position>L</symbol-position>
        <classification-value>A</classification-value>
        <action-date>
          <date>20150504</date>
        </action-date>
        <generating-office>
          <country>EP</country>
        </generating-office>
        <classification-status>B</classification-status>
        <classification-data-source>H</classification-data-source>
      </classification-cpc>
      <classification-cpc sequence="5">
        <text>A47L2401/20        20130101 LA20150504BHEP        </text>
        <cpc-version-indicator>
          <date>20130101</date>
        </cpc-version-indicator>
        <section>A</section>
        <class>47</class>
        <subclass>L</subclass>
        <main-group>2401</main-group>
        <subgroup>20</subgroup>
        <symbol-position>L</symbol-position>
        <classification-value>A</classification-value>
        <action-date>
          <date>20150504</date>
        </action-date>
        <generating-office>
          <country>EP</country>
        </generating-office>
        <classification-status>B</classification-status>
        <classification-data-source>H</classification-data-source>
      </classification-cpc>
      <classification-cpc sequence="6">
        <text>A47L2501/03        20130101 LA20140428BHEP        </text>
        <cpc-version-indicator>
          <date>20130101</date>
        </cpc-version-indicator>
        <section>A</section>
        <class>47</class>
        <subclass>L</subclass>
        <main-group>2501</main-group>
        <subgroup>03</subgroup>
        <symbol-position>L</symbol-position>
        <classification-value>A</classification-value>
        <action-date>
          <date>20140428</date>
        </action-date>
        <generating-office>
          <country>EP</country>
        </generating-office>
        <classification-status>B</classification-status>
        <classification-data-source>H</classification-data-source>
      </classification-cpc>
      <classification-cpc sequence="7">
        <text>A47L2501/04        20130101 LA20140428BHEP        </text>
        <cpc-version-indicator>
          <date>20130101</date>
        </cpc-version-indicator>
        <section>A</section>
        <class>47</class>
        <subclass>L</subclass>
        <main-group>2501</main-group>
        <subgroup>04</subgroup>
        <symbol-position>L</symbol-position>
        <classification-value>A</classification-value>
        <action-date>
          <date>20140428</date>
        </action-date>
        <generating-office>
          <country>EP</country>
        </generating-office>
        <classification-status>B</classification-status>
        <classification-data-source>H</classification-data-source>
      </classification-cpc>
      <classification-cpc sequence="8">
        <text>A47L2501/05        20130101 LA20150126BHEP        </text>
        <cpc-version-indicator>
          <date>20130101</date>
        </cpc-version-indicator>
        <section>A</section>
        <class>47</class>
        <subclass>L</subclass>
        <main-group>2501</main-group>
        <subgroup>05</subgroup>
        <symbol-position>L</symbol-position>
        <classification-value>A</classification-value>
        <action-date>
          <date>20150126</date>
        </action-date>
        <generating-office>
          <country>EP</country>
        </generating-office>
        <classification-status>B</classification-status>
        <classification-data-source>H</classification-data-source>
      </classification-cpc>
    </classifications-cpc>
    <number-of-claims calculated="yes">6</number-of-claims>
    <invention-title id="title_ger" date-changed="20151104" lang="ger" format="original">GESCHIRRREINIGUNGSVERFAHREN</invention-title>
    <invention-title id="title_eng" date-changed="20151104" lang="eng" format="original">DISH WASHING METHOD</invention-title>
    <invention-title id="title_fre" date-changed="20151104" lang="fre" format="original">PROCÉDÉ DE LAVAGE DE VAISSELLE</invention-title>
    <references-cited date-changed="20151110">
      <patent-citations name="patcit" date-changed="20151110" />
      <citation>
        <patcit num="1" dnum="DE102011075020A1" dnum-type="publication number">
          <document-id>
            <country>DE</country>
            <doc-number>102011075020</doc-number>
            <kind>A1</kind>
            <name>BSH BOSCH SIEMENS HAUSGERAETE [DE]</name>
            <date>20121031</date>
          </document-id>
          <application-date>
            <date>20110429</date>
          </application-date>
        </patcit>
        <category>X</category>
      </citation>
      <citation>
        <patcit num="2" dnum="DE2911005A1" dnum-type="publication number">
          <document-id>
            <country>DE</country>
            <doc-number>2911005</doc-number>
            <kind>A1</kind>
            <name>LICENTIA GMBH</name>
            <date>19800925</date>
          </document-id>
          <application-date>
            <date>19790321</date>
          </application-date>
        </patcit>
        <category>X</category>
      </citation>
    </references-cited>
    <related-documents date-changed="20151104">
      <division>
        <relation>
          <parent-doc>
            <document-id>
              <country>EP</country>
              <doc-number>13199631.6</doc-number>
              <date>20131227</date>
            </document-id>
          </parent-doc>
          <child-doc>
            <document-id>
              <country>EP</country>
              <doc-number>15164721</doc-number>
              <date>20131227</date>
            </document-id>
          </child-doc>
        </relation>
      </division>
    </related-documents>
    <parties date-changed="20151104">
      <applicants>
        <applicant sequence="1" app-type="applicant">
          <addressbook lang="eng">
            <orgname>Indesit Company S.p.A.</orgname>
            <registered-number>101040537</registered-number>
            <issuing-office>European Patent Office</issuing-office>
            <address>
              <address-1>Viale A. Merloni 47</address-1>
              <city>60044 Fabriano (AN)</city>
              <country>IT</country>
            </address>
          </addressbook>
        </applicant>
      </applicants>
      <inventors>
        <inventor sequence="1">
          <addressbook lang="eng">
            <name>Barus, Silvia</name>
            <address>
              <address-1>Via San Domenico 42</address-1>
              <city>10122 Torino</city>
              <country>IT</country>
            </address>
          </addressbook>
        </inventor>
        <inventor sequence="2">
          <addressbook lang="eng">
            <name>Benedetto, Gianluca</name>
            <address>
              <address-1>Via Chiusedda 78</address-1>
              <city>07024 La Maddalena (Sassari)</city>
              <country>IT</country>
            </address>
          </addressbook>
        </inventor>
        <inventor sequence="3">
          <addressbook lang="eng">
            <name>Ten Bok, Marco</name>
            <address>
              <address-1>Via Chiappero 23</address-1>
              <city>10064 Pinerolo (Torino)</city>
              <country>IT</country>
            </address>
          </addressbook>
        </inventor>
      </inventors>
      <agents>
        <agent sequence="1" rep-type="attorney">
          <addressbook lang="eng">
            <name>Monelli, Alberto</name>
            <registered-number>101176416</registered-number>
            <issuing-office>European Patent Office</issuing-office>
            <address>
              <address-1>c/o BUGNION S.P.A Largo Michele Novaro, 1/A</address-1>
              <city>43121 PARMA ITALY</city>
              <country>IT</country>
            </address>
          </addressbook>
        </agent>
      </agents>
    </parties>
    <designation-of-states date-changed="20151104">
      <designation-epc>
        <contracting-states>
          <country>AL</country>
          <country>AT</country>
          <country>BE</country>
          <country>BG</country>
          <country>CH</country>
          <country>CY</country>
          <country>CZ</country>
          <country>DE</country>
          <country>DK</country>
          <country>EE</country>
          <country>ES</country>
          <country>FI</country>
          <country>FR</country>
          <country>GB</country>
          <country>GR</country>
          <country>HR</country>
          <country>HU</country>
          <country>IE</country>
          <country>IS</country>
          <country>IT</country>
          <country>LI</country>
          <country>LT</country>
          <country>LU</country>
          <country>LV</country>
          <country>MC</country>
          <country>MK</country>
          <country>MT</country>
          <country>NL</country>
          <country>NO</country>
          <country>PL</country>
          <country>PT</country>
          <country>RO</country>
          <country>RS</country>
          <country>SE</country>
          <country>SI</country>
          <country>SK</country>
          <country>SM</country>
          <country>TR</country>
        </contracting-states>
        <extension-states>
          <country>BA</country>
          <country>ME</country>
        </extension-states>
      </designation-epc>
    </designation-of-states>
    <patent-family date-changed="20151203">
      <main-family family-id="166761000">
        <family-member>
          <document-id>
            <country>EP</country>
            <doc-number>2756788</doc-number>
            <kind>A3</kind>
            <date>20141029</date>
          </document-id>
          <application-date>
            <date>20131227</date>
          </application-date>
        </family-member>
        <family-member>
          <document-id>
            <country>EP</country>
            <doc-number>2756788</doc-number>
            <kind>A2</kind>
            <date>20140723</date>
          </document-id>
          <application-date>
            <date>20131227</date>
          </application-date>
        </family-member>
        <family-member>
          <document-id>
            <country>EP</country>
            <doc-number>2939585</doc-number>
            <kind>A1</kind>
            <date>20151104</date>
          </document-id>
          <application-date>
            <date>20131227</date>
          </application-date>
        </family-member>
        <family-member>
          <document-id>
            <country>EP</country>
            <doc-number>2949256</doc-number>
            <kind>A1</kind>
            <date>20151202</date>
          </document-id>
          <application-date>
            <date>20131227</date>
          </application-date>
        </family-member>
      </main-family>
      <complete-family family-id="166474687">
        <family-member>
          <document-id>
            <country>EP</country>
            <doc-number>2756788</doc-number>
            <kind>A3</kind>
            <date>20141029</date>
          </document-id>
          <application-date>
            <date>20131227</date>
          </application-date>
        </family-member>
        <family-member>
          <document-id>
            <country>IT</country>
            <doc-number>PR20120093</doc-number>
            <kind>A1</kind>
            <date>20140629</date>
          </document-id>
          <application-date>
            <date>20121228</date>
          </application-date>
        </family-member>
        <family-member>
          <document-id>
            <country>EP</country>
            <doc-number>2756788</doc-number>
            <kind>A2</kind>
            <date>20140723</date>
          </document-id>
          <application-date>
            <date>20131227</date>
          </application-date>
        </family-member>
        <family-member>
          <document-id>
            <country>EP</country>
            <doc-number>2939585</doc-number>
            <kind>A1</kind>
            <date>20151104</date>
          </document-id>
          <application-date>
            <date>20131227</date>
          </application-date>
        </family-member>
        <family-member>
          <document-id>
            <country>EP</country>
            <doc-number>2949256</doc-number>
            <kind>A1</kind>
            <date>20151202</date>
          </document-id>
          <application-date>
            <date>20131227</date>
          </application-date>
        </family-member>
        <family-member>
          <document-id>
            <country>IT</country>
            <doc-number>PR20120092</doc-number>
            <kind>A1</kind>
            <date>20140629</date>
          </document-id>
          <application-date>
            <date>20121228</date>
          </application-date>
        </family-member>
      </complete-family>
    </patent-family>
  </bibliographic-data>
  <abstract id="abstr_eng" date-changed="20151104" lang="eng" format="original">
    <p id="p-a-00001-en" num="0000">The method for washing dishes placed in a washing compartment (2) housing only two racks (4, 5), comprising the steps of:<br /> -setting the bottom spraying of a lower rack (4) through first bottom spraying means (6);<br /> -setting the bottom spraying of an upper rack (5), positioned above said lower rack (4), through second bottom spraying means (7);<br /> -acting on a selector (11) to switch the supply of a washing liquid at least between a first conduit (9a) which supplies the first spraying means (6) and a second conduit (9b) which supplies the second spraying means (7);<br /> -setting the top spraying of said upper rack (5) through top spraying means (8) positioned above said upper rack (5) and supplied through a third conduit (9c) which connects them to said selector (11); the step of setting the top spraying of said upper rack (5) comprising a step of removing the dirt built up in said third conduit (9c) during the change from the spraying of the lower rack (4) to the spraying of the upper rack (5) or vice versa. <img id="imga-00001-en" wi="78" he="87" img-content="drawing" file="imgaf001.tif" img-format="tif" /></p>
  </abstract>
  <description id="descr_eng" lang="eng" format="original" date-changed="20151104">
    <p id="p-00001-en" num="0001">The present invention relates to a dish washing method.</p>
    <p id="p-00002-en" num="0002">It is known a washing method according to the preamble of claim 1.</p>
    <p id="p-00003-en" num="0003">In particular, it is an object of the present invention to make available a method of washing dishes which is capable of solving the problem of the build-up of dirt in the dishwasher.</p>
    <p id="p-00004-en" num="0004">The object set forth above, and yet others, are fully achieved by the washing method according to the present invention, which is characterised by what is contained in the claims set forth below.</p>
    <p id="p-00005-en" num="0005">The technical characteristics of the invention, according to the aforementioned object, can be clearly seen from the contents of the claims set forth below, and the advantages thereof will more fully emerge from the detailed description which follows, made with reference to the accompanying drawings, which represent a purely exemplary and non-limiting embodiment, wherein: <ul id="ul-00001-en" list-style="dash" compact="compact"><li><figref>figure 1</figref> shows an open dishwasher (i.e. in which the door has been removed), according to the present invention, in a side view;</li><li><figref>figure 2</figref> shows several components (spraying means) of the dishwasher of <figref>figure 1</figref>, in a side view;</li><li><figref>figure 3</figref> shows several components (top spraying means) of the dishwasher of <figref>figure 1</figref>, in perspective view;</li><li><figref>figure 4</figref> shows several components (sprinkler) of the dishwasher of <figref>figure 1</figref>, in an exploded perspective view;</li><li><figref>figure 5</figref> shows the qualitative progress of the temperature as a function of time (along the horizontal axis) relating to the ECO programme of the dishwasher of <figref>figure 1</figref>.</li></ul></p>
    <p id="p-00006-en" num="0006">With reference to the drawings, no. 1 indicates a dishwasher comprising a box-shaped casing 2, substantially in the shape of a parallelepiped, defining a washing compartment 3. Inside the washing compartment 3 are two racks 4, 5 destined for housing the dishes to be washed.</p>
    <p id="p-00007-en" num="0007">In particular, the following can be distinguished: <ul id="ul-00002-en" list-style="dash" compact="compact"><li>a lower rack 4 slidable on a pair of rails (not shown) positioned in proximity to the bottom 2a of the box-shaped casing 2;</li><li>an upper rack 5 positioned above the lower rack 4 and slidable on a pair of rails (not shown) positioned on lateral walls 2b, 2c of the box-shaped casing 2.</li></ul></p>
    <p id="p-00008-en" num="0008">These racks 4, 5 are the only racks present in the dishwasher 1. In particular the expression 'racks' in the course of this treatment is intended to mean support means for the dishes to be washed which slide along guides formed along the box-shaped casing 2. Opportunely these racks are perforated, being obtained by intersection of filiform elements. They have overall dimensions which almost completely occupy a horizontal level of the box-shaped casing 2. Any accessories applicable to said racks to increase their load capacity or make them suitable for housing particular types of dishes (for example tiltable flaps or cutlery containers) are to be considered an integral part of said racks and are not to be considered distinct racks.</p>
    <p id="p-00009-en" num="0009">The dishwasher 1 comprises spraying means 6, 7, 8 arranged inside the washing compartment 3 and capable of spraying washing liquid on the dishes contained in the two racks 4, 5. In particular, the washing liquid comprises water and detergents (cleaning agents, finisher etc.). After coming into contact with the dishes to be washed, the washing liquid also comprises the dirt removed from the dishes to be washed (for example residues of food or condiments).</p>
    <p id="p-00010-en" num="0010">The dishwasher 1 comprises furthermore conveying means 9 suitable for connecting the washing compartment 3 to the spraying means 6, 7, 8. Preferably, the conveying means 9 connect the bottom 2a of the box-shaped casing 2 to the spraying means 6, 7, 8. The dishwasher 1 comprises a motorised pump 10 operatively active on the conveying means 9 to take the washing liquid from the washing compartment 3 and send it to the spraying means 6, 7, 8.</p>
    <p id="p-00011-en" num="0011">The washing liquid sprayed by the spraying means 6, 7, 8 builds up by gravity on the bottom 2a of the box-shaped casing 2, where it is picked up by the motorised pump 10 and sent again to the spraying means 6, 7, 8 via the conveying means.</p>
    <p id="p-00012-en" num="0012">The spraying means 6, 7, 8 comprise first bottom spraying means 6, second bottom spraying means 7 and top spraying means 8. The first bottom spraying means 6 are situated below the lower rack 4. The first bottom spraying means 7 are situated below the upper rack 5. The top spraying means 8 are positioned above the upper rack 5.</p>
    <p id="p-00013-en" num="0013">Preferably, the top spraying means 8 consist of a sprinkler comprising an impeller 12, a ring nut 13 and a cage 14 attachable to the ring 13 in such a way as to form a housing receptacle 15 for the impeller 12.</p>
    <p id="p-00014-en" num="0014">The cage 14 has a pin 16 having an end 16a of conical shape. The impeller 12 has a through hole 17 in such a way as to be able to be rotatably mounted on the pin 16 of the cage 14.</p>
    <p id="p-00015-en" num="0015">During the rotation of the impeller 12 around the pin 16, the flow of washing liquid diverges ("umbrella" opening).</p>
    <p id="p-00016-en" num="0016">Preferably, the sprinkler 8 is attached to the conveying means 9 by rotation of the ring nut 13 through a quarter of a turn.</p>
    <p id="p-00017-en" num="0017">The dishwasher 1 comprises a selector 11 operatively active over the conveying means 9 to selectively open a first route 9a towards the first bottom spraying means 6 or a second route 9b towards the second bottom spraying means 7 or a third route 9c towards the top spraying means 8 in such a way that the washing liquid is sprayed from the selected sprayer.</p>
    <p id="p-00018-en" num="0018">In the event of opening of the first route 9a or the second route 9b, the motorised pump 10 operates at a rotation speed comprised between 2300 and 2600 revolutions per minute.</p>
    <p id="p-00019-en" num="0019">In the event of opening of the third route 9c, the motorised pump 10 operates at between 1500 and 2500 revolutions per minute.</p>
    <p id="p-00020-en" num="0020">As will be better explained below, the selector 11 is formed of a fixed disc and a rotating disc superimposed.</p>
    <p id="p-00021-en" num="0021">The procedure for washing dishes placed in a washing compartment housing only two racks is described below.</p>
    <p id="p-00022-en" num="0022">This method is used both in ECO washing programmes (or cycles) and in normal programmes (i.e. non-ECO). Preferably, the proposed procedure is used for washing dishes positioned in the racks 4, 5 in such a way as to have the concavity facing downwards.</p>
    <p id="p-00023-en" num="0023">This procedure provides for the following steps: <ul id="ul-00003-en" list-style="dash" compact="compact"><li>setting a bottom spraying of the lower rack 4 through the first bottom spraying means 6;</li><li>setting a bottom spraying of the upper rack 5 via the second bottom spraying means 7;</li><li>acting on the selector 11 to switch the supply of the washing liquid at least between a first conduit 9a which supplies the first spraying means 6 and a second conduit 9b which supplies the second spraying means 7.</li></ul></p>
    <p id="p-00024-en" num="0024">Opportunely the method comprises a first step of setting a top spraying of said upper rack 5 via the top spraying means 8 positioned above said upper rack 5 and supplied via the third conduit 9c. The third conduit 9c connects the spraying means 8 to said selector 11. The step of setting a top spraying of said upper rack 5 comprises a step of removing the dirt built up in said third conduit 9c during the change from spraying the lower rack 4 to spraying the upper rack 5 or vice versa. In fact the selector 11 comprises a fixed disc comprising at least one hole and a movable disc comprising a plurality of holes. Depending on which hole in the movable disc is superimposed on the hole in the fixed disc, the first or second or third conduit 9a, 9b, 9c is supplied. To switch the flow from the first to the second conduit 9a, 9b or vice versa, the movable disc rotates and during this rotation the hole in the fixed disc is superimposed for a brief space of time on the hole which supplies the third conduit 9c, causing the introduction of a small quantity of water (often dirty) which stagnates in the third conduit 9c.</p>
    <p id="p-00025-en" num="0025">Bottom spraying of the lower rack 4 and bottom spraying of the upper rack 5 are carried out alternately several consecutive times in such a way as to form a step of bottom spraying.</p>
    <p id="p-00026-en" num="0026">The step of removing the dirt built up in the third conduit 9c is performed before and/or after this step of bottom washing. In particular it is performed at the end of a ramping up of the heating of the washing liquid. It can also be performed after a long step (for example greater than 30 minutes) in which said step of bottom washing is performed.</p>
    <p id="p-00027-en" num="0027">The duration of the step of bottom washing is greater by an order of magnitude than the duration of the step of removing the dirt built up in the third conduit 9c.</p>
    <p id="p-00028-en" num="0028">Preferably, both the bottom spraying of the lower rack 4 and the bottom spraying of the upper rack 5 have a duration comprised between about one minute and about five minutes, while the bottom washing (which is given by the multiple alternation of these sprayings) has a duration comprised between about twelve minutes and fifty-six minutes.</p>
    <p id="p-00029-en" num="0029">The step of removing the dirt built up in the third conduit 9c has a duration comprised between about one minute and about five minutes.</p>
    <p id="p-00030-en" num="0030">The embodiment here described and illustrated refers to a programme or cycle of ECO type thus composed.</p>
    <p id="p-00031-en" num="0031">The washing liquid is loaded into the washing compartment 3 during a first loading step.</p>
    <p id="p-00032-en" num="0032">Subsequently, the step of bottom washing is actuated for a duration comprised between 25 and 40 minutes during which the temperature of the washing liquid is kept constant between 20 and 25 °C for a first interval comprised between 10 and 20 minutes (see reference "a" in <figref>figure 5</figref>) and is heated up to a temperature comprised between 45° and 55°C in a second interval of duration comprised between 10 and 20 minutes (see reference "b" in <figref>figure 5</figref>).</p>
    <p id="p-00033-en" num="0033">There follows the step of removing the dirt built up in the third conduit 9c, having a duration comprised between 1 and 5 minutes (see reference "c" in <figref>figure 5</figref>).</p>
    <p id="p-00034-en" num="0034">Subsequently, the step of bottom washing is performed again for a total duration comprised between 50 and 60 minutes during which the temperature of the washing liquid is kept constant (see reference "d" in <figref>figure 5</figref>). There follows the step of removing the dirt built up in the third conduit 9c, having a duration comprised between 1 and 5 minutes (see reference "e" in <figref>figure 5</figref>).</p>
    <p id="p-00035-en" num="0035">The succession of steps of bottom washing for the first time, removing the dirt from the third conduit for the first time, bottom washing for the second time and removing the dirt from the third conduit for the second time constitute the so-called ECO cycle "wash".</p>
    <p id="p-00036-en" num="0036">The ECO cycle comprises furthermore the so-called "cold rinsing" (see reference "f") and the so-called "hot rinsing" (see reference "g"), which are not explained in detail because they do not constitute the subject of the patent.</p>
    <p id="p-00037-en" num="0037">In alternative embodiments, the step of removing the dirt from the main conduit can be performed even during the "cold rinsing" or during the "hot rinsing".</p>
    <p id="p-00038-en" num="0038">From the description given the characteristics are clear of the dishwasher and of the method for washing dishes placed in a washing compartment housing only two racks, according to the present invention, and the advantages are also clear.</p>
    <p id="p-00039-en" num="0039">In particular, the problem of the build-up of dirt, due to momentary undesired selections of the holes by the selector, is resolved thanks to the activation of the top spraying means (sprinkler).</p>
    <p id="p-00040-en" num="0040">Furthermore, activating the sprinkler at the end of the ramping-up of the heating exploits the descaling power of heat.</p>
    <p id="p-00041-en" num="0041">Furthermore, good cleaning of the main conduit is achieved by activating the sprinkler even after the last step of bottom washing, which is very long and therefore entails a considerable build-up of dirt in the conduit itself. Since the activation of the sprinkler occurs for brief periods compared with the activation of the bottom spraying means (there is a difference of an order of magnitude), the dirt introduced by the activation of the sprinkler is negligible.</p>
    <p id="p-00042-en" num="0042">Furthermore, being positioned above the upper rack, the sprinkler makes it possible to complete the washing of the dishes by spraying from above (the other sprayers are positioned below the relative racks).</p>
  </description>
  <claims id="claims_eng" lang="eng" format="original" date-changed="20151104">
    <claim num="1" id="clm-00001-en" independent="true">
      <claim-text>The method for washing dishes placed in a washing compartment (2) housing only two racks (4, 5), comprising the steps of:
<claim-text>setting the bottom spraying of a lower rack (4) through first bottom spraying means (6);</claim-text><claim-text>setting the bottom spraying of an upper rack (5), positioned above said lower rack (4), through second bottom spraying means (7);</claim-text><claim-text>acting on a selector (11) to switch the supply of a washing liquid at least between a first conduit (9a) which supplies the first spraying means (6) and a second conduit (9b) which supplies the second spraying means (7);</claim-text><claim-text><b>characterised in that</b> it comprises a step of setting the top spraying of said upper rack (5) through top spraying means (8) positioned above said upper rack (5) and supplied through a third conduit (9c) which connects them to said selector (11); the step of setting the top spraying of said upper rack (5) comprising a step of removing the dirt built up in said third conduit (9c) during the change from the spraying of the lower rack (4) to the spraying of the upper rack (5) or vice versa.</claim-text></claim-text>
    </claim>
    <claim num="2" id="clm-00002-en">
      <claim-text>The method according to claim 1, wherein the step of setting the bottom spraying of the lower rack (4) and the step of setting the bottom spraying of the upper rack (5) alternate a few consecutive times so as to define a bottom washing step, said step of removing the dirt built up in the third conduit (9c) being performed at least after said bottom washing step.</claim-text>
    </claim>
    <claim num="3" id="clm-00003-en">
      <claim-text>The method according to claim 2, wherein the duration of the step of bottom washing is greater by an order of magnitude than the duration of the step of removing the dirt built up in the third conduit (9c).</claim-text>
    </claim>
    <claim num="4" id="clm-00004-en">
      <claim-text>The method according to claim 2 or 3, wherein both the bottom spraying of the lower rack (4) and the bottom spraying of the upper rack (5) have a duration comprised between about one minute and about five minutes, while the bottom washing (which is given by the multiple alternation of these sprayings) has a duration comprised between about twelve minutes and fifty-six minutes.</claim-text>
    </claim>
    <claim num="5" id="clm-00005-en" independent="true">
      <claim-text>The method according to any one of the claims from 2 to 4, wherein the step of removing the dirt built up in the third conduit (9c) has a duration comprised between about one minute and about five minutes.</claim-text>
    </claim>
    <claim num="6" id="clm-00006-en" independent="true">
      <claim-text>The method according to any one of the claims from 2 to 5, wherein the bottom washing step is actuated for an overall duration comprised between 25 and 40 minutes during which the temperature of the washing liquid is kept constant between 20 and 25 °C for a first interval of time comprised between 10 and 20 minutes and is heated to a temperature comprised between 45 and 55 °C for a second interval of time comprised between 10 and 20 minutes, said bottom washing step being followed by the step of removing the dirt built up in the third conduit (9c) for an overall duration comprised between 1 and 5 minutes, by a further bottom washing step for an overall duration comprised between 50 and 60 minutes during which the temperature of the washing liquid is kept constant, and by a further step of removing the dirt built up in the third conduit (9c) for a duration comprised between 1 and 5 minutes.</claim-text>
    </claim>
  </claims>
  <drawings id="drawings" format="original">
    <figure num="1">
      <img he="N/A" wi="N/A" file="EP2939585A1_00001.PNG" alt="clipped image" img-content="drawing" img-format="png" original="imgaf001.tif" />
    </figure>
    <figure num="2">
      <img he="N/A" wi="N/A" file="EP2939585A1_00002.PNG" alt="drawing sheet" img-content="drawing" img-format="png" original="imgf0001.tif" />
    </figure>
    <figure num="3">
      <img he="N/A" wi="N/A" file="EP2939585A1_00003.PNG" alt="drawing sheet" img-content="drawing" img-format="png" original="imgf0002.tif" />
    </figure>
    <figure num="4">
      <img he="N/A" wi="N/A" file="EP2939585A1_00004.PNG" alt="drawing sheet" img-content="drawing" img-format="png" original="imgf0003.tif" />
    </figure>
    <figure num="5">
      <img he="N/A" wi="N/A" file="EP2939585A1_00005.PNG" alt="drawing sheet" img-content="drawing" img-format="png" original="imgf0004.tif" />
    </figure>
    <figure num="6">
      <img he="N/A" wi="N/A" file="EP2939585A1_00006.PNG" alt="drawing sheet" img-content="drawing" img-format="png" original="imgf0005.tif" />
    </figure>
    <figure num="7">
      <img he="N/A" wi="N/A" file="EP2939585A1_00007.PNG" alt="thumbnail image" img-content="drawing" img-format="png" original="imgaf001.tif" />
    </figure>
  </drawings>
  <image file="EP2939585A1.PDF" type="pdf" size="240114" pages="11" />
</lexisnexis-patent-document>