<?xml version="1.0" encoding="utf-8"?>
<!-- Copyright ©2016 LexisNexis Univentio, The Netherlands. -->
<lexisnexis-patent-document schema-version="1.13" date-produced="20160127" file="EP2938628A1.xml" produced-by="LexisNexis-Univentio" lang="eng" date-inserted="20151104" time-inserted="091040" date-changed="20151105" time-changed="044220">
  <bibliographic-data lang="eng">
    <publication-reference publ-type="Application" publ-desc="Application published with search report">
      <document-id id="121939181">
        <country>EP</country>
        <doc-number>2938628</doc-number>
        <kind>A1</kind>
        <date>20151104</date>
      </document-id>
    </publication-reference>
    <application-reference>
      <document-id>
        <country>EP</country>
        <doc-number>13868583</doc-number>
        <date>20131224</date>
      </document-id>
    </application-reference>
    <language-of-filing>eng</language-of-filing>
    <language-of-publication>eng</language-of-publication>
    <priority-claims date-changed="20151104">
      <priority-claim sequence="1" kind="international">
        <country>WO</country>
        <doc-number>CN12087339</doc-number>
        <date>20121224</date>
      </priority-claim>
      <priority-claim sequence="2" kind="international">
        <country>WO</country>
        <doc-number>CN12087336</doc-number>
        <date>20121224</date>
      </priority-claim>
      <priority-claim sequence="3" kind="international">
        <country>WO</country>
        <doc-number>CN12087345</doc-number>
        <date>20121224</date>
      </priority-claim>
      <priority-claim sequence="1" data-format="docdb">
        <country>CN</country>
        <doc-number>2012087339</doc-number>
        <kind>W</kind>
        <date>20121224</date>
        <priority-active-indicator>true</priority-active-indicator>
      </priority-claim>
      <priority-claim sequence="2" data-format="docdb">
        <country>CN</country>
        <doc-number>2012087336</doc-number>
        <kind>W</kind>
        <date>20121224</date>
        <priority-active-indicator>true</priority-active-indicator>
      </priority-claim>
      <priority-claim sequence="3" data-format="docdb">
        <country>CN</country>
        <doc-number>2012087345</doc-number>
        <kind>W</kind>
        <date>20121224</date>
        <priority-active-indicator>true</priority-active-indicator>
      </priority-claim>
      <priority-claim sequence="4" data-format="docdb">
        <country>CN</country>
        <doc-number>2013090355</doc-number>
        <kind>W</kind>
        <date>20131224</date>
        <priority-active-indicator>false</priority-active-indicator>
      </priority-claim>
      <priority-claim sequence="1" data-format="original">
        <doc-number>PCT/CN2012/087339</doc-number>
      </priority-claim>
      <priority-claim sequence="2" data-format="original">
        <doc-number>PCT/CN2012/087336</doc-number>
      </priority-claim>
      <priority-claim sequence="3" data-format="original">
        <doc-number>PCT/CN2012/087345</doc-number>
      </priority-claim>
      <priority-claim sequence="4" data-format="original">
        <doc-number>2013090355</doc-number>
      </priority-claim>
      <priority-claim sequence="1" data-format="epodoc">
        <doc-number>WO2012CN87339</doc-number>
      </priority-claim>
      <priority-claim sequence="2" data-format="epodoc">
        <doc-number>WO2012CN87336</doc-number>
      </priority-claim>
      <priority-claim sequence="3" data-format="epodoc">
        <doc-number>WO2012CN87345</doc-number>
      </priority-claim>
      <priority-claim sequence="4" data-format="epodoc">
        <doc-number>WO2013CN90355</doc-number>
      </priority-claim>
    </priority-claims>
    <dates-of-public-availability date-changed="20151105">
      <gazette-reference>
        <date>20151104</date>
      </gazette-reference>
      <unexamined-printed-without-grant>
        <date>20151104</date>
      </unexamined-printed-without-grant>
      <examined-printed-without-grant>
        <date>20151104</date>
      </examined-printed-without-grant>
    </dates-of-public-availability>
    <dates-rights-effective date-changed="20151105">
      <request-for-examination>
        <date>20150724</date>
      </request-for-examination>
    </dates-rights-effective>
    <classifications-ipcr date-changed="20151105">
      <classification-ipcr sequence="1">
        <text>C07K  14/37        20060101AFI20140718BHEP        </text>
        <ipc-version-indicator>
          <date>20060101</date>
        </ipc-version-indicator>
        <classification-level>A</classification-level>
        <section>C</section>
        <class>07</class>
        <subclass>K</subclass>
        <main-group>14</main-group>
        <subgroup>37</subgroup>
        <symbol-position>F</symbol-position>
        <classification-value>I</classification-value>
        <action-date>
          <date>20140718</date>
        </action-date>
        <generating-office>
          <country>EP</country>
        </generating-office>
        <classification-status>B</classification-status>
        <classification-data-source>H</classification-data-source>
      </classification-ipcr>
      <classification-ipcr sequence="2">
        <text>C12N   9/46        20060101ALI20140718BHEP        </text>
        <ipc-version-indicator>
          <date>20060101</date>
        </ipc-version-indicator>
        <classification-level>A</classification-level>
        <section>C</section>
        <class>12</class>
        <subclass>N</subclass>
        <main-group>9</main-group>
        <subgroup>46</subgroup>
        <symbol-position>L</symbol-position>
        <classification-value>I</classification-value>
        <action-date>
          <date>20140718</date>
        </action-date>
        <generating-office>
          <country>EP</country>
        </generating-office>
        <classification-status>B</classification-status>
        <classification-data-source>H</classification-data-source>
      </classification-ipcr>
      <classification-ipcr sequence="3">
        <text>C12N  15/56        20060101ALI20140718BHEP        </text>
        <ipc-version-indicator>
          <date>20060101</date>
        </ipc-version-indicator>
        <classification-level>A</classification-level>
        <section>C</section>
        <class>12</class>
        <subclass>N</subclass>
        <main-group>15</main-group>
        <subgroup>56</subgroup>
        <symbol-position>L</symbol-position>
        <classification-value>I</classification-value>
        <action-date>
          <date>20140718</date>
        </action-date>
        <generating-office>
          <country>EP</country>
        </generating-office>
        <classification-status>B</classification-status>
        <classification-data-source>H</classification-data-source>
      </classification-ipcr>
      <classification-ipcr sequence="4">
        <text>C12N  15/63        20060101ALI20140718BHEP        </text>
        <ipc-version-indicator>
          <date>20060101</date>
        </ipc-version-indicator>
        <classification-level>A</classification-level>
        <section>C</section>
        <class>12</class>
        <subclass>N</subclass>
        <main-group>15</main-group>
        <subgroup>63</subgroup>
        <symbol-position>L</symbol-position>
        <classification-value>I</classification-value>
        <action-date>
          <date>20140718</date>
        </action-date>
        <generating-office>
          <country>EP</country>
        </generating-office>
        <classification-status>B</classification-status>
        <classification-data-source>H</classification-data-source>
      </classification-ipcr>
    </classifications-ipcr>
    <classifications-cpc date-changed="20151105">
      <classification-cpc sequence="1">
        <text>C07K  14/37        20130101 FI20141224BHEP        </text>
        <cpc-version-indicator>
          <date>20130101</date>
        </cpc-version-indicator>
        <section>C</section>
        <class>07</class>
        <subclass>K</subclass>
        <main-group>14</main-group>
        <subgroup>37</subgroup>
        <symbol-position>F</symbol-position>
        <classification-value>I</classification-value>
        <action-date>
          <date>20141224</date>
        </action-date>
        <generating-office>
          <country>EP</country>
        </generating-office>
        <classification-status>B</classification-status>
        <classification-data-source>H</classification-data-source>
      </classification-cpc>
      <classification-cpc sequence="2">
        <text>C12N   9/2437      20130101 LI20141222BHEP        </text>
        <cpc-version-indicator>
          <date>20130101</date>
        </cpc-version-indicator>
        <section>C</section>
        <class>12</class>
        <subclass>N</subclass>
        <main-group>9</main-group>
        <subgroup>2437</subgroup>
        <symbol-position>L</symbol-position>
        <classification-value>I</classification-value>
        <action-date>
          <date>20141222</date>
        </action-date>
        <generating-office>
          <country>EP</country>
        </generating-office>
        <classification-status>B</classification-status>
        <classification-data-source>H</classification-data-source>
      </classification-cpc>
    </classifications-cpc>
    <invention-title id="title_ger" date-changed="20151104" lang="ger" format="original">POLYPEPTIDE MIT ENDOGLUCANASEAKTIVITÄT UND POLYNUKLEOTIDE ZUR CODIERUNG DAVON</invention-title>
    <invention-title id="title_eng" date-changed="20151104" lang="eng" format="original">POLYPEPTIDES HAVING ENDOGLUCANASE ACTIVITY AND POLYNUCLEOTIDES ENCODING SAME</invention-title>
    <invention-title id="title_fre" date-changed="20151104" lang="fre" format="original">POLYPEPTIDES PRÉSENTANT UNE ACTIVITÉ D'ENDOGLUCANASE ET POLYNUCLÉOTIDES CODANT POUR CEUX-CI</invention-title>
    <parties date-changed="20151104">
      <applicants>
        <applicant sequence="1" app-type="applicant">
          <addressbook lang="eng">
            <orgname>Novozymes A/S</orgname>
            <registered-number>100730107</registered-number>
            <issuing-office>European Patent Office</issuing-office>
            <address>
              <address-1>Krogshoejvej 36</address-1>
              <city>2880 Bagsvaerd</city>
              <country>DK</country>
            </address>
          </addressbook>
        </applicant>
      </applicants>
      <inventors>
        <inventor sequence="1">
          <addressbook lang="eng">
            <name>LIU, Ye</name>
            <address>
              <address-1>No. 14 Zizhuyuan Road Haidian District</address-1>
              <city>Beijing 100044</city>
              <country>CN</country>
            </address>
          </addressbook>
        </inventor>
        <inventor sequence="2">
          <addressbook lang="eng">
            <name>TANG, Lan</name>
            <address>
              <address-1>Zhichun Road 57-1-707 Haidian District</address-1>
              <city>Beijing 100080</city>
              <country>CN</country>
            </address>
          </addressbook>
        </inventor>
        <inventor sequence="3">
          <addressbook lang="eng">
            <name>LAI, Weijian</name>
            <address>
              <address-1>Apt. 407 Bldg. 5 Yongshanli Fengtai District</address-1>
              <city>Beijing 100071</city>
              <country>CN</country>
            </address>
          </addressbook>
        </inventor>
      </inventors>
    </parties>
    <designation-of-states date-changed="20151104">
      <designation-epc>
        <contracting-states>
          <country>AL</country>
          <country>AT</country>
          <country>BE</country>
          <country>BG</country>
          <country>CH</country>
          <country>CY</country>
          <country>CZ</country>
          <country>DE</country>
          <country>DK</country>
          <country>EE</country>
          <country>ES</country>
          <country>FI</country>
          <country>FR</country>
          <country>GB</country>
          <country>GR</country>
          <country>HR</country>
          <country>HU</country>
          <country>IE</country>
          <country>IS</country>
          <country>IT</country>
          <country>LI</country>
          <country>LT</country>
          <country>LU</country>
          <country>LV</country>
          <country>MC</country>
          <country>MK</country>
          <country>MT</country>
          <country>NL</country>
          <country>NO</country>
          <country>PL</country>
          <country>PT</country>
          <country>RO</country>
          <country>RS</country>
          <country>SE</country>
          <country>SI</country>
          <country>SK</country>
          <country>SM</country>
          <country>TR</country>
        </contracting-states>
        <extension-states>
          <country>BA</country>
          <country>ME</country>
        </extension-states>
      </designation-epc>
    </designation-of-states>
    <pct-or-regional-filing-data>
      <document-id>
        <country>WO</country>
        <doc-number>CN13090355</doc-number>
        <date>20131224</date>
      </document-id>
    </pct-or-regional-filing-data>
    <pct-or-regional-publishing-data>
      <document-id>
        <country>WO</country>
        <doc-number>2014101753</doc-number>
        <date>20140703</date>
      </document-id>
    </pct-or-regional-publishing-data>
    <patent-family date-changed="20151104">
      <main-family family-id="166465005">
        <family-member>
          <document-id>
            <country>US</country>
            <doc-number>20150299682</doc-number>
            <kind>A1</kind>
            <date>20151022</date>
          </document-id>
          <application-date>
            <date>20131224</date>
          </application-date>
        </family-member>
        <family-member>
          <document-id>
            <country>EP</country>
            <doc-number>2938628</doc-number>
            <kind>A1</kind>
            <date>20151104</date>
          </document-id>
          <application-date>
            <date>20131224</date>
          </application-date>
        </family-member>
        <family-member>
          <document-id>
            <country>WO</country>
            <doc-number>2014101753</doc-number>
            <kind>A1</kind>
            <date>20140703</date>
          </document-id>
          <application-date>
            <date>20131224</date>
          </application-date>
        </family-member>
      </main-family>
      <complete-family family-id="166465004">
        <family-member>
          <document-id>
            <country>US</country>
            <doc-number>20150299682</doc-number>
            <kind>A1</kind>
            <date>20151022</date>
          </document-id>
          <application-date>
            <date>20131224</date>
          </application-date>
        </family-member>
        <family-member>
          <document-id>
            <country>EP</country>
            <doc-number>2938628</doc-number>
            <kind>A1</kind>
            <date>20151104</date>
          </document-id>
          <application-date>
            <date>20131224</date>
          </application-date>
        </family-member>
        <family-member>
          <document-id>
            <country>WO</country>
            <doc-number>2014101753</doc-number>
            <kind>A1</kind>
            <date>20140703</date>
          </document-id>
          <application-date>
            <date>20131224</date>
          </application-date>
        </family-member>
      </complete-family>
    </patent-family>
  </bibliographic-data>
  <abstract id="abstr_eng" date-changed="20151105" lang="eng" format="equivalent" country="WO" doc-number="2014101753" kind="A1">
    <p>Provided are isolated polypeptides having endoglucanase activity, catalytic domains, carbohydrate binding modules and polynucleotides encoding the polypeptides, catalytic domains or carbohydrate binding modules. Also provided are nucleic acid constructs, vectors and host cells comprising the polynucleotides as well as methods of producing and using the polypeptides, catalytic domains or carbohydrate binding modules.</p>
  </abstract>
</lexisnexis-patent-document>